{
    "lastUpdated": "2026-03-01 15:12:07",
    "games": [
        {
            "id": "401820771",
            "awayTeam": "#11 Virginia Cavaliers",
            "awayScore": "51",
            "awayLogo": "https://a.espncdn.com/i/teamlogos/ncaa/500/258.png",
            "awayAbbr": "UVA",
            "homeTeam": "#1 Duke Blue Devils",
            "homeScore": "77",
            "homeLogo": "https://a.espncdn.com/i/teamlogos/ncaa/500/150.png",
            "homeAbbr": "DUKE",
            "status": "Final",
            "tv": "ESPN",
            "winProb": 0.5,
            "state": "post"
        },
        {
            "id": "401827707",
            "awayTeam": "#14 Kansas Jayhawks",
            "awayScore": "61",
            "awayLogo": "https://a.espncdn.com/i/teamlogos/ncaa/500/2305.png",
            "awayAbbr": "KU",
            "homeTeam": "#2 Arizona Wildcats",
            "homeScore": "84",
            "homeLogo": "https://a.espncdn.com/i/teamlogos/ncaa/500/12.png",
            "homeAbbr": "ARIZ",
            "status": "Final",
            "tv": "ESPN",
            "winProb": 0.5,
            "state": "post"
        },
        {
            "id": "401827712",
            "awayTeam": "#16 Texas Tech Red Raiders",
            "awayScore": "82",
            "awayLogo": "https://a.espncdn.com/i/teamlogos/ncaa/500/2641.png",
            "awayAbbr": "TTU",
            "homeTeam": "#4 Iowa State Cyclones",
            "homeScore": "73",
            "homeLogo": "https://a.espncdn.com/i/teamlogos/ncaa/500/66.png",
            "homeAbbr": "ISU",
            "status": "Final",
            "tv": "CBS",
            "winProb": 0.5,
            "state": "post"
        },
        {
            "id": "401808266",
            "awayTeam": "#20 Arkansas Razorbacks",
            "awayScore": "77",
            "awayLogo": "https://a.espncdn.com/i/teamlogos/ncaa/500/8.png",
            "awayAbbr": "ARK",
            "homeTeam": "#7 Florida Gators",
            "homeScore": "111",
            "homeLogo": "https://a.espncdn.com/i/teamlogos/ncaa/500/57.png",
            "homeAbbr": "FLA",
            "status": "Final",
            "tv": "ESPN",
            "winProb": 0.5,
            "state": "post"
        },
        {
            "id": "401829265",
            "awayTeam": "#9 Gonzaga Bulldogs",
            "awayScore": "59",
            "awayLogo": "https://a.espncdn.com/i/teamlogos/ncaa/500/2250.png",
            "awayAbbr": "GONZ",
            "homeTeam": "Saint Mary's Gaels",
            "homeScore": "70",
            "homeLogo": "https://a.espncdn.com/i/teamlogos/ncaa/500/2608.png",
            "homeAbbr": "SMC",
            "status": "Final",
            "tv": "ESPN",
            "winProb": 0.5,
            "state": "post"
        },
        {
            "id": "401825548",
            "awayTeam": "#12 Nebraska Cornhuskers",
            "awayScore": "82",
            "awayLogo": "https://a.espncdn.com/i/teamlogos/ncaa/500/158.png",
            "awayAbbr": "NEB",
            "homeTeam": "USC Trojans",
            "homeScore": "67",
            "homeLogo": "https://a.espncdn.com/i/teamlogos/ncaa/500/30.png",
            "homeAbbr": "USC",
            "status": "Final",
            "tv": "BTN",
            "winProb": 0.5,
            "state": "post"
        },
        {
            "id": "401822962",
            "awayTeam": "Villanova Wildcats",
            "awayScore": "57",
            "awayLogo": "https://a.espncdn.com/i/teamlogos/ncaa/500/222.png",
            "awayAbbr": "VILL",
            "homeTeam": "#15 St. John's Red Storm",
            "homeScore": "89",
            "homeLogo": "https://a.espncdn.com/i/teamlogos/ncaa/500/2599.png",
            "homeAbbr": "SJU",
            "status": "Final",
            "tv": "FOX",
            "winProb": 0.5,
            "state": "post"
        },
        {
            "id": "401808271",
            "awayTeam": "#17 Alabama Crimson Tide",
            "awayScore": "71",
            "awayLogo": "https://a.espncdn.com/i/teamlogos/ncaa/500/333.png",
            "awayAbbr": "ALA",
            "homeTeam": "#22 Tennessee Volunteers",
            "homeScore": "69",
            "homeLogo": "https://a.espncdn.com/i/teamlogos/ncaa/500/2633.png",
            "homeAbbr": "TENN",
            "status": "Final",
            "tv": "ESPN",
            "winProb": 0.5,
            "state": "post"
        },
        {
            "id": "401820774",
            "awayTeam": "Virginia Tech Hokies",
            "awayScore": "82",
            "awayLogo": "https://a.espncdn.com/i/teamlogos/ncaa/500/259.png",
            "awayAbbr": "VT",
            "homeTeam": "#18 North Carolina Tar Heels",
            "homeScore": "89",
            "homeLogo": "https://a.espncdn.com/i/teamlogos/ncaa/500/153.png",
            "homeAbbr": "UNC",
            "status": "Final",
            "tv": "ESPN2",
            "winProb": 0.5,
            "state": "post"
        },
        {
            "id": "401827714",
            "awayTeam": "#19 BYU Cougars",
            "awayScore": "71",
            "awayLogo": "https://a.espncdn.com/i/teamlogos/ncaa/500/252.png",
            "awayAbbr": "BYU",
            "homeTeam": "West Virginia Mountaineers",
            "homeScore": "79",
            "homeLogo": "https://a.espncdn.com/i/teamlogos/ncaa/500/277.png",
            "homeAbbr": "WVU",
            "status": "Final",
            "tv": "FOX",
            "winProb": 0.5,
            "state": "post"
        },
        {
            "id": "401820770",
            "awayTeam": "#24 Louisville Cardinals",
            "awayScore": "75",
            "awayLogo": "https://a.espncdn.com/i/teamlogos/ncaa/500/97.png",
            "awayAbbr": "LOU",
            "homeTeam": "Clemson Tigers",
            "homeScore": "80",
            "homeLogo": "https://a.espncdn.com/i/teamlogos/ncaa/500/228.png",
            "homeAbbr": "CLEM",
            "status": "Final",
            "tv": "ESPN2",
            "winProb": 0.5,
            "state": "post"
        },
        {
            "id": "401808268",
            "awayTeam": "#25 Vanderbilt Commodores",
            "awayScore": "77",
            "awayLogo": "https://a.espncdn.com/i/teamlogos/ncaa/500/238.png",
            "awayAbbr": "VAN",
            "homeTeam": "Kentucky Wildcats",
            "homeScore": "91",
            "homeLogo": "https://a.espncdn.com/i/teamlogos/ncaa/500/96.png",
            "homeAbbr": "UK",
            "status": "Final",
            "tv": "ESPN",
            "winProb": 0.5,
            "state": "post"
        },
        {
            "id": "401808270",
            "awayTeam": "Missouri Tigers",
            "awayScore": "88",
            "awayLogo": "https://a.espncdn.com/i/teamlogos/ncaa/500/142.png",
            "awayAbbr": "MIZ",
            "homeTeam": "Mississippi State Bulldogs",
            "homeScore": "64",
            "homeLogo": "https://a.espncdn.com/i/teamlogos/ncaa/500/344.png",
            "homeAbbr": "MSST",
            "status": "Final",
            "tv": "SEC Network",
            "winProb": 0.5,
            "state": "post"
        },
        {
            "id": "401804951",
            "awayTeam": "New Mexico State Aggies",
            "awayScore": "85",
            "awayLogo": "https://a.espncdn.com/i/teamlogos/ncaa/500/166.png",
            "awayAbbr": "NMSU",
            "homeTeam": "Middle Tennessee Blue Raiders",
            "homeScore": "86",
            "homeLogo": "https://a.espncdn.com/i/teamlogos/ncaa/500/2393.png",
            "homeAbbr": "MTSU",
            "status": "Final/OT",
            "tv": "ESPN+",
            "winProb": 0.5,
            "state": "post"
        },
        {
            "id": "401827710",
            "awayTeam": "Oklahoma State Cowboys",
            "awayScore": "68",
            "awayLogo": "https://a.espncdn.com/i/teamlogos/ncaa/500/197.png",
            "awayAbbr": "OKST",
            "homeTeam": "Cincinnati Bearcats",
            "homeScore": "91",
            "homeLogo": "https://a.espncdn.com/i/teamlogos/ncaa/500/2132.png",
            "homeAbbr": "CIN",
            "status": "Final",
            "tv": "CBSSN",
            "winProb": 0.5,
            "state": "post"
        },
        {
            "id": "401825545",
            "awayTeam": "UCLA Bruins",
            "awayScore": "73",
            "awayLogo": "https://a.espncdn.com/i/teamlogos/ncaa/500/26.png",
            "awayAbbr": "UCLA",
            "homeTeam": "Minnesota Golden Gophers",
            "homeScore": "78",
            "homeLogo": "https://a.espncdn.com/i/teamlogos/ncaa/500/135.png",
            "homeAbbr": "MINN",
            "status": "Final",
            "tv": "FS1",
            "winProb": 0.5,
            "state": "post"
        },
        {
            "id": "401823785",
            "awayTeam": "San Diego State Aztecs",
            "awayScore": "76",
            "awayLogo": "https://a.espncdn.com/i/teamlogos/ncaa/500/21.png",
            "awayAbbr": "SDSU",
            "homeTeam": "New Mexico Lobos",
            "homeScore": "81",
            "homeLogo": "https://a.espncdn.com/i/teamlogos/ncaa/500/167.png",
            "homeAbbr": "UNM",
            "status": "Final",
            "tv": "CBS",
            "winProb": 0.5,
            "state": "post"
        },
        {
            "id": "401812091",
            "awayTeam": "William & Mary Tribe",
            "awayScore": "91",
            "awayLogo": "https://a.espncdn.com/i/teamlogos/ncaa/500/2729.png",
            "awayAbbr": "W&M",
            "homeTeam": "North Carolina A&T Aggies",
            "homeScore": "88",
            "homeLogo": "https://a.espncdn.com/i/teamlogos/ncaa/500/2448.png",
            "homeAbbr": "NCAT",
            "status": "Final",
            "tv": "FloSports",
            "winProb": 0.5,
            "state": "post"
        },
        {
            "id": "401807768",
            "awayTeam": "Queens University Royals",
            "awayScore": "79",
            "awayLogo": "https://a.espncdn.com/i/teamlogos/ncaa/500/2511.png",
            "awayAbbr": "QUC",
            "homeTeam": "Central Arkansas Bears",
            "homeScore": "84",
            "homeLogo": "https://a.espncdn.com/i/teamlogos/ncaa/500/2110.png",
            "homeAbbr": "CARK",
            "status": "Final",
            "tv": "ESPN+",
            "winProb": 0.5,
            "state": "post"
        },
        {
            "id": "401807767",
            "awayTeam": "North Alabama Lions",
            "awayScore": "63",
            "awayLogo": "https://a.espncdn.com/i/teamlogos/ncaa/500/2453.png",
            "awayAbbr": "UNA",
            "homeTeam": "West Georgia Wolves",
            "homeScore": "75",
            "homeLogo": "https://a.espncdn.com/i/teamlogos/ncaa/500/2698.png",
            "homeAbbr": "WGA",
            "status": "Final",
            "tv": "ESPN+",
            "winProb": 0.5,
            "state": "post"
        },
        {
            "id": "401806512",
            "awayTeam": "Tennessee State Tigers",
            "awayScore": "67",
            "awayLogo": "https://a.espncdn.com/i/teamlogos/ncaa/500/2634.png",
            "awayAbbr": "TNST",
            "homeTeam": "UT Martin Skyhawks",
            "homeScore": "42",
            "homeLogo": "https://a.espncdn.com/i/teamlogos/ncaa/500/2630.png",
            "homeAbbr": "UTM",
            "status": "Final",
            "tv": "ESPNU",
            "winProb": 0.5,
            "state": "post"
        },
        {
            "id": "401804952",
            "awayTeam": "UTEP Miners",
            "awayScore": "65",
            "awayLogo": "https://a.espncdn.com/i/teamlogos/ncaa/500/2638.png",
            "awayAbbr": "UTEP",
            "homeTeam": "Western Kentucky Hilltoppers",
            "homeScore": "97",
            "homeLogo": "https://a.espncdn.com/i/teamlogos/ncaa/500/98.png",
            "homeAbbr": "WKU",
            "status": "Final",
            "tv": "ESPN+",
            "winProb": 0.5,
            "state": "post"
        },
        {
            "id": "401827708",
            "awayTeam": "Utah Utes",
            "awayScore": "60",
            "awayLogo": "https://a.espncdn.com/i/teamlogos/ncaa/500/254.png",
            "awayAbbr": "UTAH",
            "homeTeam": "Arizona State Sun Devils",
            "homeScore": "73",
            "homeLogo": "https://a.espncdn.com/i/teamlogos/ncaa/500/9.png",
            "homeAbbr": "ASU",
            "status": "Final",
            "tv": "TNT, truTV",
            "winProb": 0.5,
            "state": "post"
        },
        {
            "id": "401808469",
            "awayTeam": "Northern Arizona Lumberjacks",
            "awayScore": "57",
            "awayLogo": "https://a.espncdn.com/i/teamlogos/ncaa/500/2464.png",
            "awayAbbr": "NAU",
            "homeTeam": "Eastern Washington Eagles",
            "homeScore": "88",
            "homeLogo": "https://a.espncdn.com/i/teamlogos/ncaa/500/331.png",
            "homeAbbr": "EWU",
            "status": "Final",
            "tv": "ESPN+",
            "winProb": 0.5,
            "state": "post"
        },
        {
            "id": "401807766",
            "awayTeam": "Lipscomb Bisons",
            "awayScore": "80",
            "awayLogo": "https://a.espncdn.com/i/teamlogos/ncaa/500/288.png",
            "awayAbbr": "LIP",
            "homeTeam": "Eastern Kentucky Colonels",
            "homeScore": "77",
            "homeLogo": "https://a.espncdn.com/i/teamlogos/ncaa/500/2198.png",
            "homeAbbr": "EKU",
            "status": "Final",
            "tv": "ESPN+",
            "winProb": 0.5,
            "state": "post"
        },
        {
            "id": "401808272",
            "awayTeam": "Texas Longhorns",
            "awayScore": "76",
            "awayLogo": "https://a.espncdn.com/i/teamlogos/ncaa/500/251.png",
            "awayAbbr": "TEX",
            "homeTeam": "Texas A&M Aggies",
            "homeScore": "70",
            "homeLogo": "https://a.espncdn.com/i/teamlogos/ncaa/500/245.png",
            "homeAbbr": "TA&M",
            "status": "Final",
            "tv": "ESPN2",
            "winProb": 0.5,
            "state": "post"
        },
        {
            "id": "401830245",
            "awayTeam": "North Carolina Central Eagles",
            "awayScore": "74",
            "awayLogo": "https://a.espncdn.com/i/teamlogos/ncaa/500/2428.png",
            "awayAbbr": "NCCU",
            "homeTeam": "Delaware State Hornets",
            "homeScore": "60",
            "homeLogo": "https://a.espncdn.com/i/teamlogos/ncaa/500/2169.png",
            "homeAbbr": "DSU",
            "status": "Final",
            "tv": "ESPN+",
            "winProb": 0.5,
            "state": "post"
        },
        {
            "id": "401809389",
            "awayTeam": "East Tennessee State Buccaneers",
            "awayScore": "76",
            "awayLogo": "https://a.espncdn.com/i/teamlogos/ncaa/500/2193.png",
            "awayAbbr": "ETSU",
            "homeTeam": "Mercer Bears",
            "homeScore": "82",
            "homeLogo": "https://a.espncdn.com/i/teamlogos/ncaa/500/2382.png",
            "homeAbbr": "MER",
            "status": "Final",
            "tv": "ESPN+",
            "winProb": 0.5,
            "state": "post"
        },
        {
            "id": "401806511",
            "awayTeam": "Tennessee Tech Golden Eagles",
            "awayScore": "73",
            "awayLogo": "https://a.espncdn.com/i/teamlogos/ncaa/500/2635.png",
            "awayAbbr": "TNTC",
            "homeTeam": "Southeast Missouri State Redhawks",
            "homeScore": "89",
            "homeLogo": "https://a.espncdn.com/i/teamlogos/ncaa/500/2546.png",
            "homeAbbr": "SEMO",
            "status": "Final",
            "tv": "ESPN+",
            "winProb": 0.5,
            "state": "post"
        },
        {
            "id": "401822964",
            "awayTeam": "Providence Friars",
            "awayScore": "79",
            "awayLogo": "https://a.espncdn.com/i/teamlogos/ncaa/500/2507.png",
            "awayAbbr": "PROV",
            "homeTeam": "Creighton Bluejays",
            "homeScore": "76",
            "homeLogo": "https://a.espncdn.com/i/teamlogos/ncaa/500/156.png",
            "homeAbbr": "CREI",
            "status": "Final",
            "tv": "TNT, truTV",
            "winProb": 0.5,
            "state": "post"
        },
        {
            "id": "401808722",
            "awayTeam": "East Texas A&M Lions",
            "awayScore": "55",
            "awayLogo": "https://a.espncdn.com/i/teamlogos/ncaa/500/2837.png",
            "awayAbbr": "ETAM",
            "homeTeam": "UT Rio Grande Valley Vaqueros",
            "homeScore": "63",
            "homeLogo": "https://a.espncdn.com/i/teamlogos/ncaa/500/292.png",
            "homeAbbr": "RGV",
            "status": "Final",
            "tv": "ESPN+",
            "winProb": 0.5,
            "state": "post"
        },
        {
            "id": "401804954",
            "awayTeam": "Missouri State Bears",
            "awayScore": "81",
            "awayLogo": "https://a.espncdn.com/i/teamlogos/ncaa/500/2623.png",
            "awayAbbr": "MOST",
            "homeTeam": "Sam Houston Bearkats",
            "homeScore": "86",
            "homeLogo": "https://a.espncdn.com/i/teamlogos/ncaa/500/2534.png",
            "homeAbbr": "SHSU",
            "status": "Final",
            "tv": "ESPN+",
            "winProb": 0.5,
            "state": "post"
        },
        {
            "id": "401828669",
            "awayTeam": "Jackson State Tigers",
            "awayScore": "57",
            "awayLogo": "https://a.espncdn.com/i/teamlogos/ncaa/500/2296.png",
            "awayAbbr": "JKST",
            "homeTeam": "Texas Southern Tigers",
            "homeScore": "82",
            "homeLogo": "https://a.espncdn.com/i/teamlogos/ncaa/500/2640.png",
            "homeAbbr": "TXSO",
            "status": "Final",
            "tv": "N/A",
            "winProb": 0.5,
            "state": "post"
        },
        {
            "id": "401827169",
            "awayTeam": "Alabama State Hornets",
            "awayScore": "89",
            "awayLogo": "https://a.espncdn.com/i/teamlogos/ncaa/500/2011.png",
            "awayAbbr": "ALST",
            "homeTeam": "Alabama A&M Bulldogs",
            "homeScore": "88",
            "homeLogo": "https://a.espncdn.com/i/teamlogos/ncaa/500/2010.png",
            "homeAbbr": "AAMU",
            "status": "Final",
            "tv": "N/A",
            "winProb": 0.5,
            "state": "post"
        },
        {
            "id": "401820776",
            "awayTeam": "SMU Mustangs",
            "awayScore": "75",
            "awayLogo": "https://a.espncdn.com/i/teamlogos/ncaa/500/2567.png",
            "awayAbbr": "SMU",
            "homeTeam": "Stanford Cardinal",
            "homeScore": "95",
            "homeLogo": "https://a.espncdn.com/i/teamlogos/ncaa/500/24.png",
            "homeAbbr": "STAN",
            "status": "Final",
            "tv": "ACC Network",
            "winProb": 0.5,
            "state": "post"
        },
        {
            "id": "401827713",
            "awayTeam": "TCU Horned Frogs",
            "awayScore": "77",
            "awayLogo": "https://a.espncdn.com/i/teamlogos/ncaa/500/2628.png",
            "awayAbbr": "TCU",
            "homeTeam": "Kansas State Wildcats",
            "homeScore": "68",
            "homeLogo": "https://a.espncdn.com/i/teamlogos/ncaa/500/2306.png",
            "homeAbbr": "KSU",
            "status": "Final",
            "tv": "ESPN2",
            "winProb": 0.5,
            "state": "post"
        },
        {
            "id": "401827150",
            "awayTeam": "Mississippi Valley State Delta Devils",
            "awayScore": "70",
            "awayLogo": "https://a.espncdn.com/i/teamlogos/ncaa/500/2400.png",
            "awayAbbr": "MVSU",
            "homeTeam": "Arkansas-Pine Bluff Golden Lions",
            "homeScore": "69",
            "homeLogo": "https://a.espncdn.com/i/teamlogos/ncaa/500/2029.png",
            "homeAbbr": "UAPB",
            "status": "Final",
            "tv": "N/A",
            "winProb": 0.5,
            "state": "post"
        },
        {
            "id": "401808946",
            "awayTeam": "Northwestern State Demons",
            "awayScore": "59",
            "awayLogo": "https://a.espncdn.com/i/teamlogos/ncaa/500/2466.png",
            "awayAbbr": "NWST",
            "homeTeam": "Texas A&M-Corpus Christi Islanders",
            "homeScore": "71",
            "homeLogo": "https://a.espncdn.com/i/teamlogos/ncaa/500/357.png",
            "homeAbbr": "AMCC",
            "status": "Final",
            "tv": "ESPN+",
            "winProb": 0.5,
            "state": "post"
        },
        {
            "id": "401817687",
            "awayTeam": "Wright State Raiders",
            "awayScore": "92",
            "awayLogo": "https://a.espncdn.com/i/teamlogos/ncaa/500/2750.png",
            "awayAbbr": "WRST",
            "homeTeam": "Northern Kentucky Norse",
            "homeScore": "91",
            "homeLogo": "https://a.espncdn.com/i/teamlogos/ncaa/500/94.png",
            "homeAbbr": "NKU",
            "status": "Final",
            "tv": "ESPN+",
            "winProb": 0.5,
            "state": "post"
        },
        {
            "id": "401827709",
            "awayTeam": "Baylor Bears",
            "awayScore": "87",
            "awayLogo": "https://a.espncdn.com/i/teamlogos/ncaa/500/239.png",
            "awayAbbr": "BAY",
            "homeTeam": "UCF Knights",
            "homeScore": "86",
            "homeLogo": "https://a.espncdn.com/i/teamlogos/ncaa/500/2116.png",
            "homeAbbr": "UCF",
            "status": "Final",
            "tv": "FS1",
            "winProb": 0.5,
            "state": "post"
        },
        {
            "id": "401818439",
            "awayTeam": "Oral Roberts Golden Eagles",
            "awayScore": "94",
            "awayLogo": "https://a.espncdn.com/i/teamlogos/ncaa/500/198.png",
            "awayAbbr": "ORU",
            "homeTeam": "Kansas City Roos",
            "homeScore": "70",
            "homeLogo": "https://a.espncdn.com/i/teamlogos/ncaa/500/140.png",
            "homeAbbr": "KC",
            "status": "Final",
            "tv": "Summit League Network, Midco Sports Plus",
            "winProb": 0.5,
            "state": "post"
        }
    ]
}