{
    "lastUpdated": "2026-03-19 01:37:15",
    "games": [
        {
            "id": "401858343",
            "awayTeam": "George Washington Revolutionaries",
            "awayScore": "66",
            "awayLogo": "https://a.espncdn.com/i/teamlogos/ncaa/500/45.png",
            "awayAbbr": "GW",
            "homeTeam": "Utah Valley Wolverines",
            "homeScore": "65",
            "homeLogo": "https://a.espncdn.com/i/teamlogos/ncaa/500/3084.png",
            "homeAbbr": "UVU",
            "status": "5:13 - 2nd Half",
            "tv": "ESPN+",
            "winProb": 0.322,
            "state": "in"
        },
        {
            "id": "401856436",
            "awayTeam": "#11 Miami (OH) RedHawks",
            "awayScore": "15",
            "awayLogo": "https://a.espncdn.com/i/teamlogos/ncaa/500/193.png",
            "awayAbbr": "M-OH",
            "homeTeam": "#11 SMU Mustangs",
            "homeScore": "13",
            "homeLogo": "https://a.espncdn.com/i/teamlogos/ncaa/500/2567.png",
            "homeAbbr": "SMU",
            "status": "9:19 - 1st Half",
            "tv": "truTV",
            "winProb": 0.679,
            "state": "in"
        },
        {
            "id": "401858342",
            "awayTeam": "Sam Houston Bearkats",
            "awayScore": "28",
            "awayLogo": "https://a.espncdn.com/i/teamlogos/ncaa/500/2534.png",
            "awayAbbr": "SHSU",
            "homeTeam": "New Mexico Lobos",
            "homeScore": "40",
            "homeLogo": "https://a.espncdn.com/i/teamlogos/ncaa/500/167.png",
            "homeAbbr": "UNM",
            "status": "5:49 - 1st Half",
            "tv": "ESPN+",
            "winProb": 0.956,
            "state": "in"
        },
        {
            "id": "401858348",
            "awayTeam": "Saint Joseph's Hawks",
            "awayScore": "0",
            "awayLogo": "https://a.espncdn.com/i/teamlogos/ncaa/500/2603.png",
            "awayAbbr": "JOES",
            "homeTeam": "Colorado State Rams",
            "homeScore": "0",
            "homeLogo": "https://a.espncdn.com/i/teamlogos/ncaa/500/36.png",
            "homeAbbr": "CSU",
            "status": "Wed, March 18th at 11:00 PM EDT",
            "tv": "ESPNU",
            "winProb": 0.5,
            "state": "pre"
        }
    ]
}