{
    "lastUpdated": "2026-03-14 06:05:20",
    "games": [
        {
            "id": "401851182",
            "awayTeam": "Clemson Tigers",
            "awayScore": "61",
            "awayLogo": "https://a.espncdn.com/i/teamlogos/ncaa/500/228.png",
            "awayAbbr": "CLEM",
            "homeTeam": "#1 Duke Blue Devils",
            "homeScore": "73",
            "homeLogo": "https://a.espncdn.com/i/teamlogos/ncaa/500/150.png",
            "homeAbbr": "DUKE",
            "status": "Final",
            "tv": "ESPN2",
            "winProb": 0.5,
            "state": "post"
        },
        {
            "id": "401851304",
            "awayTeam": "#7 Iowa State Cyclones",
            "awayScore": "80",
            "awayLogo": "https://a.espncdn.com/i/teamlogos/ncaa/500/66.png",
            "awayAbbr": "ISU",
            "homeTeam": "#2 Arizona Wildcats",
            "homeScore": "82",
            "homeLogo": "https://a.espncdn.com/i/teamlogos/ncaa/500/12.png",
            "homeAbbr": "ARIZ",
            "status": "Final",
            "tv": "ESPN",
            "winProb": 0.5,
            "state": "post"
        },
        {
            "id": "401851380",
            "awayTeam": "Ohio State Buckeyes",
            "awayScore": "67",
            "awayLogo": "https://a.espncdn.com/i/teamlogos/ncaa/500/194.png",
            "awayAbbr": "OSU",
            "homeTeam": "#3 Michigan Wolverines",
            "homeScore": "71",
            "homeLogo": "https://a.espncdn.com/i/teamlogos/ncaa/500/130.png",
            "homeAbbr": "MICH",
            "status": "Final",
            "tv": "BTN",
            "winProb": 0.5,
            "state": "post"
        },
        {
            "id": "401851565",
            "awayTeam": "Kentucky Wildcats",
            "awayScore": "63",
            "awayLogo": "https://a.espncdn.com/i/teamlogos/ncaa/500/96.png",
            "awayAbbr": "UK",
            "homeTeam": "#4 Florida Gators",
            "homeScore": "71",
            "homeLogo": "https://a.espncdn.com/i/teamlogos/ncaa/500/57.png",
            "homeAbbr": "FLA",
            "status": "Final",
            "tv": "ESPN",
            "winProb": 0.5,
            "state": "post"
        },
        {
            "id": "401851305",
            "awayTeam": "#14 Kansas Jayhawks",
            "awayScore": "47",
            "awayLogo": "https://a.espncdn.com/i/teamlogos/ncaa/500/2305.png",
            "awayAbbr": "KU",
            "homeTeam": "#5 Houston Cougars",
            "homeScore": "69",
            "homeLogo": "https://a.espncdn.com/i/teamlogos/ncaa/500/248.png",
            "homeAbbr": "HOU",
            "status": "Final",
            "tv": "ESPN",
            "winProb": 0.5,
            "state": "post"
        },
        {
            "id": "401851316",
            "awayTeam": "Georgetown Hoyas",
            "awayScore": "51",
            "awayLogo": "https://a.espncdn.com/i/teamlogos/ncaa/500/46.png",
            "awayAbbr": "GTWN",
            "homeTeam": "#6 UConn Huskies",
            "homeScore": "67",
            "homeLogo": "https://a.espncdn.com/i/teamlogos/ncaa/500/41.png",
            "homeAbbr": "CONN",
            "status": "Final",
            "tv": "FS1",
            "winProb": 0.5,
            "state": "post"
        },
        {
            "id": "401851383",
            "awayTeam": "UCLA Bruins",
            "awayScore": "88",
            "awayLogo": "https://a.espncdn.com/i/teamlogos/ncaa/500/26.png",
            "awayAbbr": "UCLA",
            "homeTeam": "#8 Michigan State Spartans",
            "homeScore": "84",
            "homeLogo": "https://a.espncdn.com/i/teamlogos/ncaa/500/127.png",
            "homeAbbr": "MSU",
            "status": "Final",
            "tv": "BTN",
            "winProb": 0.5,
            "state": "post"
        },
        {
            "id": "401851381",
            "awayTeam": "#23 Wisconsin Badgers",
            "awayScore": "91",
            "awayLogo": "https://a.espncdn.com/i/teamlogos/ncaa/500/275.png",
            "awayAbbr": "WIS",
            "homeTeam": "#9 Illinois Fighting Illini",
            "homeScore": "88",
            "homeLogo": "https://a.espncdn.com/i/teamlogos/ncaa/500/356.png",
            "homeAbbr": "ILL",
            "status": "Final/OT",
            "tv": "BTN",
            "winProb": 0.5,
            "state": "post"
        },
        {
            "id": "401851181",
            "awayTeam": "Miami Hurricanes",
            "awayScore": "62",
            "awayLogo": "https://a.espncdn.com/i/teamlogos/ncaa/500/2390.png",
            "awayAbbr": "MIA",
            "homeTeam": "#10 Virginia Cavaliers",
            "homeScore": "84",
            "homeLogo": "https://a.espncdn.com/i/teamlogos/ncaa/500/258.png",
            "homeAbbr": "UVA",
            "status": "Final",
            "tv": "ESPN2",
            "winProb": 0.5,
            "state": "post"
        },
        {
            "id": "401851382",
            "awayTeam": "#18 Purdue Boilermakers",
            "awayScore": "74",
            "awayLogo": "https://a.espncdn.com/i/teamlogos/ncaa/500/2509.png",
            "awayAbbr": "PUR",
            "homeTeam": "#11 Nebraska Cornhuskers",
            "homeScore": "58",
            "homeLogo": "https://a.espncdn.com/i/teamlogos/ncaa/500/158.png",
            "homeAbbr": "NEB",
            "status": "Final",
            "tv": "BTN",
            "winProb": 0.5,
            "state": "post"
        },
        {
            "id": "401851567",
            "awayTeam": "Ole Miss Rebels",
            "awayScore": "80",
            "awayLogo": "https://a.espncdn.com/i/teamlogos/ncaa/500/145.png",
            "awayAbbr": "MISS",
            "homeTeam": "#15 Alabama Crimson Tide",
            "homeScore": "79",
            "homeLogo": "https://a.espncdn.com/i/teamlogos/ncaa/500/333.png",
            "homeAbbr": "ALA",
            "status": "Final",
            "tv": "SEC Network",
            "winProb": 0.5,
            "state": "post"
        },
        {
            "id": "401851568",
            "awayTeam": "Oklahoma Sooners",
            "awayScore": "79",
            "awayLogo": "https://a.espncdn.com/i/teamlogos/ncaa/500/201.png",
            "awayAbbr": "OU",
            "homeTeam": "#17 Arkansas Razorbacks",
            "homeScore": "82",
            "homeLogo": "https://a.espncdn.com/i/teamlogos/ncaa/500/8.png",
            "homeAbbr": "ARK",
            "status": "Final",
            "tv": "SEC Network",
            "winProb": 0.5,
            "state": "post"
        },
        {
            "id": "401851566",
            "awayTeam": "#25 Tennessee Volunteers",
            "awayScore": "68",
            "awayLogo": "https://a.espncdn.com/i/teamlogos/ncaa/500/2633.png",
            "awayAbbr": "TENN",
            "homeTeam": "#22 Vanderbilt Commodores",
            "homeScore": "75",
            "homeLogo": "https://a.espncdn.com/i/teamlogos/ncaa/500/238.png",
            "homeAbbr": "VAN",
            "status": "Final",
            "tv": "ESPN",
            "winProb": 0.5,
            "state": "post"
        },
        {
            "id": "401851270",
            "awayTeam": "George Washington Revolutionaries",
            "awayScore": "81",
            "awayLogo": "https://a.espncdn.com/i/teamlogos/ncaa/500/45.png",
            "awayAbbr": "GW",
            "homeTeam": "Saint Louis Billikens",
            "homeScore": "88",
            "homeLogo": "https://a.espncdn.com/i/teamlogos/ncaa/500/139.png",
            "homeAbbr": "SLU",
            "status": "Final",
            "tv": "USA Net",
            "winProb": 0.5,
            "state": "post"
        },
        {
            "id": "401851413",
            "awayTeam": "Missouri State Bears",
            "awayScore": "66",
            "awayLogo": "https://a.espncdn.com/i/teamlogos/ncaa/500/2623.png",
            "awayAbbr": "MOST",
            "homeTeam": "Louisiana Tech Bulldogs",
            "homeScore": "69",
            "homeLogo": "https://a.espncdn.com/i/teamlogos/ncaa/500/2348.png",
            "homeAbbr": "LT",
            "status": "Final",
            "tv": "CBSSN",
            "winProb": 0.5,
            "state": "post"
        },
        {
            "id": "401851722",
            "awayTeam": "Prairie View A&M Panthers",
            "awayScore": "74",
            "awayLogo": "https://a.espncdn.com/i/teamlogos/ncaa/500/2504.png",
            "awayAbbr": "PV",
            "homeTeam": "Alabama A&M Bulldogs",
            "homeScore": "55",
            "homeLogo": "https://a.espncdn.com/i/teamlogos/ncaa/500/2010.png",
            "homeAbbr": "AAMU",
            "status": "Final",
            "tv": "ESPN+",
            "winProb": 0.5,
            "state": "post"
        },
        {
            "id": "401851414",
            "awayTeam": "Kennesaw State Owls",
            "awayScore": "79",
            "awayLogo": "https://a.espncdn.com/i/teamlogos/ncaa/500/338.png",
            "awayAbbr": "KENN",
            "homeTeam": "Sam Houston Bearkats",
            "homeScore": "73",
            "homeLogo": "https://a.espncdn.com/i/teamlogos/ncaa/500/2534.png",
            "homeAbbr": "SHSU",
            "status": "Final",
            "tv": "CBSSN",
            "winProb": 0.5,
            "state": "post"
        },
        {
            "id": "401851226",
            "awayTeam": "North Texas Mean Green",
            "awayScore": "84",
            "awayLogo": "https://a.espncdn.com/i/teamlogos/ncaa/500/249.png",
            "awayAbbr": "UNT",
            "homeTeam": "Tulsa Golden Hurricane",
            "homeScore": "90",
            "homeLogo": "https://a.espncdn.com/i/teamlogos/ncaa/500/202.png",
            "homeAbbr": "TLSA",
            "status": "Final/3OT",
            "tv": "ESPN2",
            "winProb": 0.5,
            "state": "post"
        },
        {
            "id": "401851476",
            "awayTeam": "Delaware State Hornets",
            "awayScore": "53",
            "awayLogo": "https://a.espncdn.com/i/teamlogos/ncaa/500/2169.png",
            "awayAbbr": "DSU",
            "homeTeam": "North Carolina Central Eagles",
            "homeScore": "59",
            "homeLogo": "https://a.espncdn.com/i/teamlogos/ncaa/500/2428.png",
            "homeAbbr": "NCCU",
            "status": "Final",
            "tv": "ESPN+",
            "winProb": 0.5,
            "state": "post"
        }
    ]
}